Workbook
Name GI: Input!$B$17
Name iAGE: Input!$B$3
Name iBP: Input!$B$8
Name In_GI: Input!$B$20
Name In_St_Yr: Input!$B$21
Name Income_End: Input!$B$22
Name Income_Int: Input!$B$19
Name Income_ST: Input!$B$18
Name IP: Input!$B$23
Name iPRM: Input!$B$9
Name iPRM_PP: Input!$B$7
Name MB: Input!$B$15
Name SA: Input!$B$16

Sheet Input
A1: Century Income - Input | I1: =VLOOKUP(iPRM_PP,H2:I4,2,0) -> 25 | J1: =VLOOKUP(iPRM_PP,H2:J4,3,0) -> 0
A2: Option | B2: Twin Income | D2: =VLOOKUP(B2,P2:Q4,2,0) -> 3 | H2: 7 | I2: 15 | J2: 20 | P2: Immediate Income | Q2: 1 | T2: 7 | U2: 7 | V2: 10 | W2: 10 | X2: 12
A3: Age of Life Assured | B3: 35 | H3: 10 | I3: 20 | J3: 25 | P3: Deferred Income | Q3: 2 | T3: 15 | U3: 20 | V3: 20 | W3: 25 | X3: 25
A4: Name of the Life Assured | B4: ABC | H4: 12 | I4: 25 | P4: Twin Income | Q4: 3 | S4: 1
A5: Age of Policy holder | B5: 35 | S5: =S4+1 -> 2
A6: Name of the Policy holder | B6: XYZ | S6: =S5+1 -> 3
A7: Premium Paying Term | B7: 12 | D7: =IF(AND(iPRM_PP=7,iBP=15),1,IF(AND(iPRM_PP=7,iBP=20),2,IF(AND(iPRM_PP=10,iBP=20),3,IF(AND(iPRM_PP=10,iBP=25),4,5)))) -> 5 | S7: =S6+1 -> 4
A8: Policy Term | B8: 25 | I8: =VLOOKUP(B10,H10:J13,2,0) -> 0.0867 | J8: =VLOOKUP(B10,H10:J13,3,0) -> 12 | S8: =S7+1 -> 5 | T8: 1.05 | U8: 1.05
A9: Annualised Premium | B9: 50000 | D9: =IF(iPRM<100000,1,IF(iPRM<150000,2,3)) -> 1 | H9: Mode of Premium | I9: Modal Factor | J9: No of Pymts | S9: =S8+1 -> 6 | T9: 1.05 | U9: 1.05
A10: Mode of Payment | B10: Monthly | H10: Yearly | I10: 1 | J10: 1 | S10: =S9+1 -> 7
A11: Annual Premium | B11: =B9*I8*J8 -> 52020 | H11: Half Yearly | I11: 0.5108 | J11: 2 | S11: =S10+1 -> 8 | V11: 1.05 | W11: 1.05
A12: Standard Age Proof | B12: No | H12: Quarterly | I12: 0.2582 | J12: 4 | S12: =S11+1 -> 9 | V12: 1.05 | W12: 1.05
A13: Distribution Channel | B13: Corporate Agency | H13: Monthly | I13: 0.0867 | J13: 12 | S13: =S12+1 -> 10 | T13: 1.05 | U13: 1.05 | X13: 1.05
A14: Staff Policy | B14: No | S14: =S13+1 -> 11 | T14: 1.05 | U14: 1.05 | X14: 1.05
A15: Sum Assured on Maturity | B15: =B9*D15*L15*I24 -> 912100 | D15: =OFFSET(IF(D2=1,MB!A2,IF(D2=2,MB!A49,MB!A96)),iAGE-17,Input!D7) -> 18.242 | H15: Channel | I15: =IF(VLOOKUP(B13,H16:K22,2,0)=0,"",VLOOKUP(B13,H16:K22,2,0)) -> Yes | J15: =IF(VLOOKUP(B13,H16:K22,3,0)=0,"",VLOOKUP(B13,H16:K22,3,0)) -> No | K15: =IF(VLOOKUP(B13,H16:K22,4,0)=0,"",VLOOKUP(B13,H16:K22,4,0)) | L15: =1+VLOOKUP(B13,H16:L22,5,0) -> 1 | S15: =S14+1 -> 12
A16: Sum Assured | B16: =B11*10 -> 520200 | H16: Corporate Agency | I16: Yes | J16: No | L16: {=IF(AND(B13=H16,B14=J16),0,INDEX(I35:K35,1,D2))} -> 0 | S16: =S15+1 -> 13 | V16: 1.05 | W16: 1.05
A17: GI Rate | B17: =IF(D2=1,10%,IF(D2=2,30%,105%)) -> 1.05 | H17: Direct Marketing | I17: Yes | J17: No | L17: {=IF(AND(B13=H17,B14=J17),0,INDEX(I36:K36,1,D2))} -> 0.085 | S17: =S16+1 -> 14 | V17: 1.05 | W17: 1.05
A18: Income Start | B18: =IF(D2=1,1,IF(D2=2,iPRM_PP+1,iPRM_PP-2)) -> 10 | H18: Online | I18: SUD Life Staff | J18: Corporate Staff | K18: No | L18: {=IF(B13=H18,IF(B14=I18,INDEX(I36:K36,1,D2),INDEX(I35:K35,1,D2)))} -> FALSE | S18: =S17+1 -> 15 | U18: 1.05 | X18: 1.05
A19: Income Interval | B19: =IF(D2=3,5,1) -> 5 | H19: Broker | L19: 0 | S19: =S18+1 -> 16 | U19: 1.05 | X19: 1.05
A20: Increase in GI | B20: =IF(D2=1,30%,IF(D2=2,10%,0)) -> 0 | H20: Agency | L20: 0 | S20: =S19+1 -> 17
A21: Increase in GI Start Years | B21: =IF(D2=3,0,Income_ST+1) -> 0 | H21: Web Aggregrator | L21: 0 | S21: =S20+1 -> 18 | V21: 1.05 | W21: 1.05
A22: Increase in GI Stop Years | B22: =IF(D2=1,iPRM_PP,iBP) -> 25 | H22: Insurance Marketing Firm | L22: 0 | S22: =S21+1 -> 19 | V22: 1.05 | W22: 1.05
A23: Installment Premium | B23: =ROUND(iPRM*I8+I8*IF(B12="No",1.5*SA/1000,0),0) -> 4403 | S23: =S22+1 -> 20 | X23: 1.05
A24: Gender | B24: Male | H24: HSAB | I24: =1+VLOOKUP(iPRM,H27:K29,MATCH(D2,H26:K26,0),TRUE) -> 1 | S24: =S23+1 -> 21 | X24: 1.05
H25: Premium | I25: Immediate Income | J25: Deferred Income | K25: Twin Income | S25: =S24+1 -> 22
I26: 1 | J26: 2 | K26: 3 | S26: =S25+1 -> 23 | W26: 1.05
H27: 50000 | I27: 0 | J27: 0 | K27: 0 | S27: =S26+1 -> 24 | W27: 1.05
H28: 100000 | I28: 0.03 | J28: 0.0225 | K28: 0.0325 | S28: =S27+1 -> 25
H29: 200000 | I29: 0.035 | J29: 0.03 | K29: 0.045
H32: Staff Benefit
H33: Type | I33: Immediate Income | J33: Deferred Income | K33: Twin Income
I34: 1 | J34: 2 | K34: 3
H35: Online/ Corporate Staff | I35: 0.0425 | J35: 0.035 | K35: 0.0425
H36: SUD Staff | I36: 0.085 | J36: 0.07 | K36: 0.085

Sheet Output
A1: Benefit Illustration
A2: (This shall form a part of the policy document)
A4: Name of Prospect/Policyholder: | C4: =Input!$B$6 -> XYZ | E4: Proposal No. :
A5: Age: | C5: =Input!$B$5 -> 35 | E5: Name of the Product: | G5: SUD Life Century Income
A6: Name of Life Assured: | C6: =Input!B4 -> ABC | E6: Tag Line: | G6: Individual Non-linked Non-participating Savings Life Insurance Plan
A7: Age: | C7: =iAGE -> 35
A8: Policy Term: | C8: =iBP -> 25 | E8: Unique Identification Number: | G8: 142N100V03
A9: Premium Payment Term: | C9: =iPRM_PP -> 12 | E9: GST Rate and applicable cess,if any : | G9: 1st Year | I9: 0
A10: Amount of Instalment Premium: | C10: =IP -> 4403 | G10: 2nd Year Onwards | I10: 0
A11: Mode of Payment of Premium: | C11: =Input!B10 -> Monthly
A13: This Benefit Illustration is intended to show the year-wise premiums payable and benefits under the policy.
A15: Policy Details
A16: Policy Option (Income Option) | B16: =Input!B2 -> Twin Income | C16: Base Plan | E16: Sum Assured Rs. | G16: =SA -> 520200
E17: Sum Assured on Death(at inception of the policy) Rs. | G17: =SA -> 520200
A19: Premium Summary
F20: Base Plan | G20: Riders | H20: Total Instalment Premium
A22: Instalment Premium without GST | F22: =IP -> 4403 | G22: NA | H22: =F22 -> 4403
A23: Instalment Premium with First Year GST | F23: =F22*I9+F22 -> 4403 | G23: NA | H23: =F23 -> 4403
A24: Instalment Premium with GST 2nd Year onwards | F24: =F22*I10+F22 -> 4403 | G24: NA | H24: =F24 -> 4403
I26: (Amount in Rupees.)
A27: Policy Year | B27: Annualized Premium | C27: Guaranteed | H27: Non Guaranteed | I27: Surrender Value [Greater of (a) or (b)]
C28: Survival Benefit | D28: Loyalty Survival benefit | E28: Maturity | F28: Death Benefit | G28: Guaranteed Surrender Value (GSV) (a) | H28: Special Surrender Value (SSV) (b)
A29: 1 | B29: =IF(A29>iPRM_PP,"",iPRM) -> 50000 | C29: =IF(A29>iBP,"",IF(A29<Income_ST,0,IF(OR(Input!$D$2=1,Input!$D$2=2),iPRM*GI,iPRM*OFFSET(Input!$S$3,Output!A29,Input!$D$7)))+IF(Input!$D$2=2,IF(AND(A29>=In_St_Yr,A29<=Income_End),GI*iPRM*In_GI*(A29-(In_St_Yr-1))))) -> 0 | D29: =IF(A29>iBP,"",IF(Input!$D$2=1,IF(AND(A29>=In_St_Yr,A29<=Income_End),SUM(Output!$C$28:C28)*In_GI,IF(A29>=Income_End,D28,0)),0)) -> 0 | E29: =IF(A29>iBP,"",IF(A29=iBP,MB,0)) -> 0 | F29: =IF(A29>iBP,"",MAX(SA,Output!I29,1.05*(Input!$B$11*IF(Output!A29>iPRM_PP,iPRM_PP,Output!A29)))) -> 520200 | G29: =IF(A29>iBP,"",MAX(0,(((Input!$B$11*IF(Output!A29>iPRM_PP,iPRM_PP,Output!A29))*OFFSET(SF!$A$3,Output!A29,Input!$D$7))-SUM($C$29:C29)-SUM($D$29:D29)))) -> 0 | H29: =IF(A29>iBP,"",SUM($B$29:B29)/SUM($B$29:$B$40)*MB*OFFSET(SF!$AC$3,A29,Input!$D$7)+(SUM($B$29:B29)/SUM($B$29:$B$40)*(IF(Input!$D$2=1,Output!C29+Output!D29,GI*iPRM)))*OFFSET(IF(Input!$D$2=1,SF!$H$3,IF(Input!$D$2=2,SF!$O$3,SF!$V$3)),A29,Input!$D$7)) -> 24615.232 | I29: =IF(A29>iBP,"",MAX(G29,H29)) -> 24615.232
A30: =A29+1 -> 2 | B30: =IF(A30>iPRM_PP,"",iPRM) -> 50000 | C30: =IF(A30>iBP,"",IF(A30<Income_ST,0,IF(OR(Input!$D$2=1,Input!$D$2=2),iPRM*GI,iPRM*OFFSET(Input!$S$3,Output!A30,Input!$D$7)))+IF(Input!$D$2=2,IF(AND(A30>=In_St_Yr,A30<=Income_End),GI*iPRM*In_GI*(A30-(In_St_Yr-1))))) -> 0 | D30: =IF(A30>iBP,"",IF(Input!$D$2=1,IF(AND(A30>=In_St_Yr,A30<=Income_End),SUM(Output!$C$28:C29)*In_GI,IF(A30>=Income_End,D29,0)),0)) -> 0 | E30: =IF(A30>iBP,"",IF(A30=iBP,MB,0)) -> 0 | F30: =IF(A30>iBP,"",MAX(SA,Output!I30,1.05*(Input!$B$11*IF(Output!A30>iPRM_PP,iPRM_PP,Output!A30)))) -> 520200 | G30: =IF(A30>iBP,"",MAX(0,(((Input!$B$11*IF(Output!A30>iPRM_PP,iPRM_PP,Output!A30))*OFFSET(SF!$A$3,Output!A30,Input!$D$7))-SUM($C$29:C30)-SUM($D$29:D30)))) -> 36414 | H30: =IF(A30>iBP,"",SUM($B$29:B30)/SUM($B$29:$B$40)*MB*OFFSET(SF!$AC$3,A30,Input!$D$7)+(SUM($B$29:B30)/SUM($B$29:$B$40)*(IF(Input!$D$2=1,Output!C30+Output!D30,GI*iPRM)))*OFFSET(IF(Input!$D$2=1,SF!$H$3,IF(Input!$D$2=2,SF!$O$3,SF!$V$3)),A30,Input!$D$7)) -> 49230.463 | I30: =IF(A30>iBP,"",MAX(G30,H30)) -> 49230.463
A31: =A30+1 -> 3 | B31: =IF(A31>iPRM_PP,"",iPRM) -> 50000 | C31: =IF(A31>iBP,"",IF(A31<Income_ST,0,IF(OR(Input!$D$2=1,Input!$D$2=2),iPRM*GI,iPRM*OFFSET(Input!$S$3,Output!A31,Input!$D$7)))+IF(Input!$D$2=2,IF(AND(A31>=In_St_Yr,A31<=Income_End),GI*iPRM*In_GI*(A31-(In_St_Yr-1))))) -> 0 | D31: =IF(A31>iBP,"",IF(Input!$D$2=1,IF(AND(A31>=In_St_Yr,A31<=Income_End),SUM(Output!$C$28:C30)*In_GI,IF(A31>=Income_End,D30,0)),0)) -> 0 | E31: =IF(A31>iBP,"",IF(A31=iBP,MB,0)) -> 0 | F31: =IF(A31>iBP,"",MAX(SA,Output!I31,1.05*(Input!$B$11*IF(Output!A31>iPRM_PP,iPRM_PP,Output!A31)))) -> 520200 | G31: =IF(A31>iBP,"",MAX(0,(((Input!$B$11*IF(Output!A31>iPRM_PP,iPRM_PP,Output!A31))*OFFSET(SF!$A$3,Output!A31,Input!$D$7))-SUM($C$29:C31)-SUM($D$29:D31)))) -> 54621 | H31: =IF(A31>iBP,"",SUM($B$29:B31)/SUM($B$29:$B$40)*MB*OFFSET(SF!$AC$3,A31,Input!$D$7)+(SUM($B$29:B31)/SUM($B$29:$B$40)*(IF(Input!$D$2=1,Output!C31+Output!D31,GI*iPRM)))*OFFSET(IF(Input!$D$2=1,SF!$H$3,IF(Input!$D$2=2,SF!$O$3,SF!$V$3)),A31,Input!$D$7)) -> 79102.94 | I31: =IF(A31>iBP,"",MAX(G31,H31)) -> 79102.94
A32: =A31+1 -> 4 | B32: =IF(A32>iPRM_PP,"",iPRM) -> 50000 | C32: =IF(A32>iBP,"",IF(A32<Income_ST,0,IF(OR(Input!$D$2=1,Input!$D$2=2),iPRM*GI,iPRM*OFFSET(Input!$S$3,Output!A32,Input!$D$7)))+IF(Input!$D$2=2,IF(AND(A32>=In_St_Yr,A32<=Income_End),GI*iPRM*In_GI*(A32-(In_St_Yr-1))))) -> 0 | D32: =IF(A32>iBP,"",IF(Input!$D$2=1,IF(AND(A32>=In_St_Yr,A32<=Income_End),SUM(Output!$C$28:C31)*In_GI,IF(A32>=Income_End,D31,0)),0)) -> 0 | E32: =IF(A32>iBP,"",IF(A32=iBP,MB,0)) -> 0 | F32: =IF(A32>iBP,"",MAX(SA,Output!I32,1.05*(Input!$B$11*IF(Output!A32>iPRM_PP,iPRM_PP,Output!A32)))) -> 520200 | G32: =IF(A32>iBP,"",MAX(0,(((Input!$B$11*IF(Output!A32>iPRM_PP,iPRM_PP,Output!A32))*OFFSET(SF!$A$3,Output!A32,Input!$D$7))-SUM($C$29:C32)-SUM($D$29:D32)))) -> 104040 | H32: =IF(A32>iBP,"",SUM($B$29:B32)/SUM($B$29:$B$40)*MB*OFFSET(SF!$AC$3,A32,Input!$D$7)+(SUM($B$29:B32)/SUM($B$29:$B$40)*(IF(Input!$D$2=1,Output!C32+Output!D32,GI*iPRM)))*OFFSET(IF(Input!$D$2=1,SF!$H$3,IF(Input!$D$2=2,SF!$O$3,SF!$V$3)),A32,Input!$D$7)) -> 112940.47 | I32: =IF(A32>iBP,"",MAX(G32,H32)) -> 112940.47
A33: =A32+1 -> 5 | B33: =IF(A33>iPRM_PP,"",iPRM) -> 50000 | C33: =IF(A33>iBP,"",IF(A33<Income_ST,0,IF(OR(Input!$D$2=1,Input!$D$2=2),iPRM*GI,iPRM*OFFSET(Input!$S$3,Output!A33,Input!$D$7)))+IF(Input!$D$2=2,IF(AND(A33>=In_St_Yr,A33<=Income_End),GI*iPRM*In_GI*(A33-(In_St_Yr-1))))) -> 0 | D33: =IF(A33>iBP,"",IF(Input!$D$2=1,IF(AND(A33>=In_St_Yr,A33<=Income_End),SUM(Output!$C$28:C32)*In_GI,IF(A33>=Income_End,D32,0)),0)) -> 0 | E33: =IF(A33>iBP,"",IF(A33=iBP,MB,0)) -> 0 | F33: =IF(A33>iBP,"",MAX(SA,Output!I33,1.05*(Input!$B$11*IF(Output!A33>iPRM_PP,iPRM_PP,Output!A33)))) -> 520200 | G33: =IF(A33>iBP,"",MAX(0,(((Input!$B$11*IF(Output!A33>iPRM_PP,iPRM_PP,Output!A33))*OFFSET(SF!$A$3,Output!A33,Input!$D$7))-SUM($C$29:C33)-SUM($D$29:D33)))) -> 130050 | H33: =IF(A33>iBP,"",SUM($B$29:B33)/SUM($B$29:$B$40)*MB*OFFSET(SF!$AC$3,A33,Input!$D$7)+(SUM($B$29:B33)/SUM($B$29:$B$40)*(IF(Input!$D$2=1,Output!C33+Output!D33,GI*iPRM)))*OFFSET(IF(Input!$D$2=1,SF!$H$3,IF(Input!$D$2=2,SF!$O$3,SF!$V$3)),A33,Input!$D$7)) -> 151228.5 | I33: =IF(A33>iBP,"",MAX(G33,H33)) -> 151228.5
A34: =A33+1 -> 6 | B34: =IF(A34>iPRM_PP,"",iPRM) -> 50000 | C34: =IF(A34>iBP,"",IF(A34<Income_ST,0,IF(OR(Input!$D$2=1,Input!$D$2=2),iPRM*GI,iPRM*OFFSET(Input!$S$3,Output!A34,Input!$D$7)))+IF(Input!$D$2=2,IF(AND(A34>=In_St_Yr,A34<=Income_End),GI*iPRM*In_GI*(A34-(In_St_Yr-1))))) -> 0 | D34: =IF(A34>iBP,"",IF(Input!$D$2=1,IF(AND(A34>=In_St_Yr,A34<=Income_End),SUM(Output!$C$28:C33)*In_GI,IF(A34>=Income_End,D33,0)),0)) -> 0 | E34: =IF(A34>iBP,"",IF(A34=iBP,MB,0)) -> 0 | F34: =IF(A34>iBP,"",MAX(SA,Output!I34,1.05*(Input!$B$11*IF(Output!A34>iPRM_PP,iPRM_PP,Output!A34)))) -> 520200 | G34: =IF(A34>iBP,"",MAX(0,(((Input!$B$11*IF(Output!A34>iPRM_PP,iPRM_PP,Output!A34))*OFFSET(SF!$A$3,Output!A34,Input!$D$7))-SUM($C$29:C34)-SUM($D$29:D34)))) -> 156060 | H34: =IF(A34>iBP,"",SUM($B$29:B34)/SUM($B$29:$B$40)*MB*OFFSET(SF!$AC$3,A34,Input!$D$7)+(SUM($B$29:B34)/SUM($B$29:$B$40)*(IF(Input!$D$2=1,Output!C34+Output!D34,GI*iPRM)))*OFFSET(IF(Input!$D$2=1,SF!$H$3,IF(Input!$D$2=2,SF!$O$3,SF!$V$3)),A34,Input!$D$7)) -> 194382.23 | I34: =IF(A34>iBP,"",MAX(G34,H34)) -> 194382.23
A35: =A34+1 -> 7 | B35: =IF(A35>iPRM_PP,"",iPRM) -> 50000 | C35: =IF(A35>iBP,"",IF(A35<Income_ST,0,IF(OR(Input!$D$2=1,Input!$D$2=2),iPRM*GI,iPRM*OFFSET(Input!$S$3,Output!A35,Input!$D$7)))+IF(Input!$D$2=2,IF(AND(A35>=In_St_Yr,A35<=Income_End),GI*iPRM*In_GI*(A35-(In_St_Yr-1))))) -> 0 | D35: =IF(A35>iBP,"",IF(Input!$D$2=1,IF(AND(A35>=In_St_Yr,A35<=Income_End),SUM(Output!$C$28:C34)*In_GI,IF(A35>=Income_End,D34,0)),0)) -> 0 | E35: =IF(A35>iBP,"",IF(A35=iBP,MB,0)) -> 0 | F35: =IF(A35>iBP,"",MAX(SA,Output!I35,1.05*(Input!$B$11*IF(Output!A35>iPRM_PP,iPRM_PP,Output!A35)))) -> 520200 | G35: =IF(A35>iBP,"",MAX(0,(((Input!$B$11*IF(Output!A35>iPRM_PP,iPRM_PP,Output!A35))*OFFSET(SF!$A$3,Output!A35,Input!$D$7))-SUM($C$29:C35)-SUM($D$29:D35)))) -> 182070 | H35: =IF(A35>iBP,"",SUM($B$29:B35)/SUM($B$29:$B$40)*MB*OFFSET(SF!$AC$3,A35,Input!$D$7)+(SUM($B$29:B35)/SUM($B$29:$B$40)*(IF(Input!$D$2=1,Output!C35+Output!D35,GI*iPRM)))*OFFSET(IF(Input!$D$2=1,SF!$H$3,IF(Input!$D$2=2,SF!$O$3,SF!$V$3)),A35,Input!$D$7)) -> 242913.91 | I35: =IF(A35>iBP,"",MAX(G35,H35)) -> 242913.91
A36: =A35+1 -> 8 | B36: =IF(A36>iPRM_PP,"",iPRM) -> 50000 | C36: =IF(A36>iBP,"",IF(A36<Income_ST,0,IF(OR(Input!$D$2=1,Input!$D$2=2),iPRM*GI,iPRM*OFFSET(Input!$S$3,Output!A36,Input!$D$7)))+IF(Input!$D$2=2,IF(AND(A36>=In_St_Yr,A36<=Income_End),GI*iPRM*In_GI*(A36-(In_St_Yr-1))))) -> 0 | D36: =IF(A36>iBP,"",IF(Input!$D$2=1,IF(AND(A36>=In_St_Yr,A36<=Income_End),SUM(Output!$C$28:C35)*In_GI,IF(A36>=Income_End,D35,0)),0)) -> 0 | E36: =IF(A36>iBP,"",IF(A36=iBP,MB,0)) -> 0 | F36: =IF(A36>iBP,"",MAX(SA,Output!I36,1.05*(Input!$B$11*IF(Output!A36>iPRM_PP,iPRM_PP,Output!A36)))) -> 520200 | G36: =IF(A36>iBP,"",MAX(0,(((Input!$B$11*IF(Output!A36>iPRM_PP,iPRM_PP,Output!A36))*OFFSET(SF!$A$3,Output!A36,Input!$D$7))-SUM($C$29:C36)-SUM($D$29:D36)))) -> 217859.76 | H36: =IF(A36>iBP,"",SUM($B$29:B36)/SUM($B$29:$B$40)*MB*OFFSET(SF!$AC$3,A36,Input!$D$7)+(SUM($B$29:B36)/SUM($B$29:$B$40)*(IF(Input!$D$2=1,Output!C36+Output!D36,GI*iPRM)))*OFFSET(IF(Input!$D$2=1,SF!$H$3,IF(Input!$D$2=2,SF!$O$3,SF!$V$3)),A36,Input!$D$7)) -> 297401.16 | I36: =IF(A36>iBP,"",MAX(G36,H36)) -> 297401.16
A37: =A36+1 -> 9 | B37: =IF(A37>iPRM_PP,"",iPRM) -> 50000 | C37: =IF(A37>iBP,"",IF(A37<Income_ST,0,IF(OR(Input!$D$2=1,Input!$D$2=2),iPRM*GI,iPRM*OFFSET(Input!$S$3,Output!A37,Input!$D$7)))+IF(Input!$D$2=2,IF(AND(A37>=In_St_Yr,A37<=Income_End),GI*iPRM*In_GI*(A37-(In_St_Yr-1))))) -> 0 | D37: =IF(A37>iBP,"",IF(Input!$D$2=1,IF(AND(A37>=In_St_Yr,A37<=Income_End),SUM(Output!$C$28:C36)*In_GI,IF(A37>=Income_End,D36,0)),0)) -> 0 | E37: =IF(A37>iBP,"",IF(A37=iBP,MB,0)) -> 0 | F37: =IF(A37>iBP,"",MAX(SA,Output!I37,1.05*(Input!$B$11*IF(Output!A37>iPRM_PP,iPRM_PP,Output!A37)))) -> 520200 | G37: =IF(A37>iBP,"",MAX(0,(((Input!$B$11*IF(Output!A37>iPRM_PP,iPRM_PP,Output!A37))*OFFSET(SF!$A$3,Output!A37,Input!$D$7))-SUM($C$29:C37)-SUM($D$29:D37)))) -> 256141.28 | H37: =IF(A37>iBP,"",SUM($B$29:B37)/SUM($B$29:$B$40)*MB*OFFSET(SF!$AC$3,A37,Input!$D$7)+(SUM($B$29:B37)/SUM($B$29:$B$40)*(IF(Input!$D$2=1,Output!C37+Output!D37,GI*iPRM)))*OFFSET(IF(Input!$D$2=1,SF!$H$3,IF(Input!$D$2=2,SF!$O$3,SF!$V$3)),A37,Input!$D$7)) -> 358403.74 | I37: =IF(A37>iBP,"",MAX(G37,H37)) -> 358403.74
A38: =A37+1 -> 10 | B38: =IF(A38>iPRM_PP,"",iPRM) -> 50000 | C38: =IF(A38>iBP,"",IF(A38<Income_ST,0,IF(OR(Input!$D$2=1,Input!$D$2=2),iPRM*GI,iPRM*OFFSET(Input!$S$3,Output!A38,Input!$D$7)))+IF(Input!$D$2=2,IF(AND(A38>=In_St_Yr,A38<=Income_End),GI*iPRM*In_GI*(A38-(In_St_Yr-1))))) -> 52500 | D38: =IF(A38>iBP,"",IF(Input!$D$2=1,IF(AND(A38>=In_St_Yr,A38<=Income_End),SUM(Output!$C$28:C37)*In_GI,IF(A38>=Income_End,D37,0)),0)) -> 0 | E38: =IF(A38>iBP,"",IF(A38=iBP,MB,0)) -> 0 | F38: =IF(A38>iBP,"",MAX(SA,Output!I38,1.05*(Input!$B$11*IF(Output!A38>iPRM_PP,iPRM_PP,Output!A38)))) -> 546210 | G38: =IF(A38>iBP,"",MAX(0,(((Input!$B$11*IF(Output!A38>iPRM_PP,iPRM_PP,Output!A38))*OFFSET(SF!$A$3,Output!A38,Input!$D$7))-SUM($C$29:C38)-SUM($D$29:D38)))) -> 244326.12 | H38: =IF(A38>iBP,"",SUM($B$29:B38)/SUM($B$29:$B$40)*MB*OFFSET(SF!$AC$3,A38,Input!$D$7)+(SUM($B$29:B38)/SUM($B$29:$B$40)*(IF(Input!$D$2=1,Output!C38+Output!D38,GI*iPRM)))*OFFSET(IF(Input!$D$2=1,SF!$H$3,IF(Input!$D$2=2,SF!$O$3,SF!$V$3)),A38,Input!$D$7)) -> 426684.18 | I38: =IF(A38>iBP,"",MAX(G38,H38)) -> 426684.18
A39: =A38+1 -> 11 | B39: =IF(A39>iPRM_PP,"",iPRM) -> 50000 | C39: =IF(A39>iBP,"",IF(A39<Income_ST,0,IF(OR(Input!$D$2=1,Input!$D$2=2),iPRM*GI,iPRM*OFFSET(Input!$S$3,Output!A39,Input!$D$7)))+IF(Input!$D$2=2,IF(AND(A39>=In_St_Yr,A39<=Income_End),GI*iPRM*In_GI*(A39-(In_St_Yr-1))))) -> 52500 | D39: =IF(A39>iBP,"",IF(Input!$D$2=1,IF(AND(A39>=In_St_Yr,A39<=Income_End),SUM(Output!$C$28:C38)*In_GI,IF(A39>=Income_End,D38,0)),0)) -> 0 | E39: =IF(A39>iBP,"",IF(A39=iBP,MB,0)) -> 0 | F39: =IF(A39>iBP,"",MAX(SA,Output!I39,1.05*(Input!$B$11*IF(Output!A39>iPRM_PP,iPRM_PP,Output!A39)))) -> 600831 | G39: =IF(A39>iBP,"",MAX(0,(((Input!$B$11*IF(Output!A39>iPRM_PP,iPRM_PP,Output!A39))*OFFSET(SF!$A$3,Output!A39,Input!$D$7))-SUM($C$29:C39)-SUM($D$29:D39)))) -> 234955.9 | H39: =IF(A39>iBP,"",SUM($B$29:B39)/SUM($B$29:$B$40)*MB*OFFSET(SF!$AC$3,A39,Input!$D$7)+(SUM($B$29:B39)/SUM($B$29:$B$40)*(IF(Input!$D$2=1,Output!C39+Output!D39,GI*iPRM)))*OFFSET(IF(Input!$D$2=1,SF!$H$3,IF(Input!$D$2=2,SF!$O$3,SF!$V$3)),A39,Input!$D$7)) -> 454798.96 | I39: =IF(A39>iBP,"",MAX(G39,H39)) -> 454798.96
A40: =A39+1 -> 12 | B40: =IF(A40>iPRM_PP,"",iPRM) -> 50000 | C40: =IF(A40>iBP,"",IF(A40<Income_ST,0,IF(OR(Input!$D$2=1,Input!$D$2=2),iPRM*GI,iPRM*OFFSET(Input!$S$3,Output!A40,Input!$D$7)))+IF(Input!$D$2=2,IF(AND(A40>=In_St_Yr,A40<=Income_End),GI*iPRM*In_GI*(A40-(In_St_Yr-1))))) -> 0 | D40: =IF(A40>iBP,"",IF(Input!$D$2=1,IF(AND(A40>=In_St_Yr,A40<=Income_End),SUM(Output!$C$28:C39)*In_GI,IF(A40>=Income_End,D39,0)),0)) -> 0 | E40: =IF(A40>iBP,"",IF(A40=iBP,MB,0)) -> 0 | F40: =IF(A40>iBP,"",MAX(SA,Output!I40,1.05*(Input!$B$11*IF(Output!A40>iPRM_PP,iPRM_PP,Output!A40)))) -> 655452 | G40: =IF(A40>iBP,"",MAX(0,(((Input!$B$11*IF(Output!A40>iPRM_PP,iPRM_PP,Output!A40))*OFFSET(SF!$A$3,Output!A40,Input!$D$7))-SUM($C$29:C40)-SUM($D$29:D40)))) -> 280530.62 | H40: =IF(A40>iBP,"",SUM($B$29:B40)/SUM($B$29:$B$40)*MB*OFFSET(SF!$AC$3,A40,Input!$D$7)+(SUM($B$29:B40)/SUM($B$29:$B$40)*(IF(Input!$D$2=1,Output!C40+Output!D40,GI*iPRM)))*OFFSET(IF(Input!$D$2=1,SF!$H$3,IF(Input!$D$2=2,SF!$O$3,SF!$V$3)),A40,Input!$D$7)) -> 478933.98 | I40: =IF(A40>iBP,"",MAX(G40,H40)) -> 478933.98
A41: =A40+1 -> 13 | B41: =IF(A41>iPRM_PP,"",iPRM) | C41: =IF(A41>iBP,"",IF(A41<Income_ST,0,IF(OR(Input!$D$2=1,Input!$D$2=2),iPRM*GI,iPRM*OFFSET(Input!$S$3,Output!A41,Input!$D$7)))+IF(Input!$D$2=2,IF(AND(A41>=In_St_Yr,A41<=Income_End),GI*iPRM*In_GI*(A41-(In_St_Yr-1))))) -> 0 | D41: =IF(A41>iBP,"",IF(Input!$D$2=1,IF(AND(A41>=In_St_Yr,A41<=Income_End),SUM(Output!$C$28:C40)*In_GI,IF(A41>=Income_End,D40,0)),0)) -> 0 | E41: =IF(A41>iBP,"",IF(A41=iBP,MB,0)) -> 0 | F41: =IF(A41>iBP,"",MAX(SA,Output!I41,1.05*(Input!$B$11*IF(Output!A41>iPRM_PP,iPRM_PP,Output!A41)))) -> 655452 | G41: =IF(A41>iBP,"",MAX(0,(((Input!$B$11*IF(Output!A41>iPRM_PP,iPRM_PP,Output!A41))*OFFSET(SF!$A$3,Output!A41,Input!$D$7))-SUM($C$29:C41)-SUM($D$29:D41)))) -> 295262.69 | H41: =IF(A41>iBP,"",SUM($B$29:B41)/SUM($B$29:$B$40)*MB*OFFSET(SF!$AC$3,A41,Input!$D$7)+(SUM($B$29:B41)/SUM($B$29:$B$40)*(IF(Input!$D$2=1,Output!C41+Output!D41,GI*iPRM)))*OFFSET(IF(Input!$D$2=1,SF!$H$3,IF(Input!$D$2=2,SF!$O$3,SF!$V$3)),A41,Input!$D$7)) -> 512638 | I41: =IF(A41>iBP,"",MAX(G41,H41)) -> 512638
... A53: =A52+1 -> 25 | B53: =IF(A53>iPRM_PP,"",iPRM) | C53: =IF(A53>iBP,"",IF(A53<Income_ST,0,IF(OR(Input!$D$2=1,Input!$D$2=2),iPRM*GI,iPRM*OFFSET(Input!$S$3,Output!A53,Input!$D$7)))+IF(Input!$D$2=2,IF(AND(A53>=In_St_Yr,A53<=Income_End),GI*iPRM*In_GI*(A53-(In_St_Yr-1))))) -> 0 | D53: =IF(A53>iBP,"",IF(Input!$D$2=1,IF(AND(A53>=In_St_Yr,A53<=Income_End),SUM(Output!$C$28:C52)*In_GI,IF(A53>=Income_End,D52,0)),0)) -> 0 | E53: =IF(A53>iBP,"",IF(A53=iBP,MB,0)) -> 912100 | F53: =IF(A53>iBP,"",MAX(SA,Output!I53,1.05*(Input!$B$11*IF(Output!A53>iPRM_PP,iPRM_PP,Output!A53)))) -> 849165.1 | G53: =IF(A53>iBP,"",MAX(0,(((Input!$B$11*IF(Output!A53>iPRM_PP,iPRM_PP,Output!A53))*OFFSET(SF!$A$3,Output!A53,Input!$D$7))-SUM($C$29:C53)-SUM($D$29:D53)))) -> 246816 | H53: =IF(A53>iBP,"",SUM($B$29:B53)/SUM($B$29:$B$40)*MB*OFFSET(SF!$AC$3,A53,Input!$D$7)+(SUM($B$29:B53)/SUM($B$29:$B$40)*(IF(Input!$D$2=1,Output!C53+Output!D53,GI*iPRM)))*OFFSET(IF(Input!$D$2=1,SF!$H$3,IF(Input!$D$2=2,SF!$O$3,SF!$V$3)),A53,Input!$D$7)) -> 849165.1 | I53: =IF(A53>iBP,"",MAX(G53,H53)) -> 849165.1
A55: Notes:Annualized Premium excludes Underwriting extra premium ,frequency loadings on premiums ,the premiums paid towards the riders ,if any and Goods and Service Tax
A57: Terms and Conditions
A58: 1. Surrender Benefit
A59: Surrender of the policy is allowed after end of the first policy year provided one full years’ premiums have been paid. During the Policy Term, Surrender Value payable will be higher of Guaranteed Surrender Value or Special Surrender Value.
A60: 2. Under Option 1 - Immediate Income - The Increase in Loyalty Survival Benefit will continue only when the policy is inforce and upto the premium payment term
A61: 3. No Rider are available under the plan.
A62: 4. Policy values are as of year end i.e it is assumed the events occur at end of the year.
A63: 5. Tax Benefits
A64: Premiums payable and benefits receivable under this plan are eligible for tax benefits as per the prevailing tax laws.Please consult your tax advisor for details
A65: 6. Proposal Deposit
A66: The proposal deposit receipt given in respect of the consideration amount paid to the company does not bind the company to accept the risk on the life of the life proposed under the proposal for insurance.
A67: 7. About Star Union Dai-ichi Life Insurance Company Limited
... A71: In case you require any clarification, please consult your insurance advisor or call our office.
A73: I…… (Name), have explained the premiums,and benefits under the product fully to the prospect/policyholder. | F73: I…………………… (Name), having received the information with respect to the above, have understood the above statement before entering into the contract.
A75: Place:
A76: Date: | B76: Signature of Agent/Intermediary/Official | F76: Date: | G76: Signature of Prospect/Policyholder

Sheet SF
A1: GSV | H1: SSV - Option 1 | O1: SSV - Option 2 | V1: SSV - Option 3 | AC1: SSV Factor1
A2: PY | B2: 7 | C2: 7 | D2: 10 | E2: 10 | F2: 12 | H2: PY | I2: 7 | K2: 10 | M2: 12 | O2: PY | P2: 7 | R2: 10 | T2: 12 | V2: PY | W2: 7 | Y2: 10 | AA2: 12 | AC2: PY | AD2: 7 | AF2: 10 | AH2: 12
B3: 15 | C3: 20 | D3: 20 | E3: 25 | F3: 25 | I3: 15 | J3: 20 | K3: 20 | L3: 25 | M3: 25 | P3: 15 | Q3: 20 | R3: 20 | S3: 25 | T3: 25 | W3: 15 | X3: 20 | Y3: 20 | Z3: 25 | AA3: 25 | AD3: 15 | AE3: 20 | AF3: 20 | AG3: 25 | AH3: 25
A4: 1 | B4: 0 | C4: 0 | D4: 0 | E4: 0 | F4: 0 | H4: 1 | I4: =I5 -> 8.403 | J4: =J5 -> 9.7966 | K4: =K5 -> 9.7966 | L4: =L5 -> 10.7258 | M4: =M5 -> 10.7258 | O4: 1 | P4: =P5 -> 4.8806 | Q4: =Q5 -> 7.6458 | R4: =R5 -> 4.7858 | S4: =S5 -> 6.8146 | T4: =T5 -> 5.1589 | V4: 1 | W4: =W5 -> 2.43 | X4: =X5 -> 3.1054 | Y4: =Y5 -> 2.4734 | Z4: =Z5 -> 2.828 | AA4: =AA5 -> 2.1204 | AC4: 1 | AD4: =AD5 -> 0.3755 | AE4: =AE5 -> 0.2714 | AF4: =AF5 -> 0.2714 | AG4: =AG5 -> 0.2018 | AH4: =AH5 -> 0.2018
A5: 2 | B5: 0.35 | C5: 0.35 | D5: 0.35 | E5: 0.35 | F5: 0.35 | H5: 2 | I5: 8.403 | J5: 9.7966 | K5: 9.7966 | L5: 10.7258 | M5: 10.7258 | O5: 2 | P5: 4.8806 | Q5: 7.6458 | R5: 4.7858 | S5: 6.8146 | T5: 5.1589 | V5: 2 | W5: 2.43 | X5: 3.1054 | Y5: 2.4734 | Z5: 2.828 | AA5: 2.1204 | AC5: 2 | AD5: 0.3755 | AE5: 0.2714 | AF5: 0.2714 | AG5: 0.2018 | AH5: 0.2018
A6: 3 | B6: 0.35 | C6: 0.35 | D6: 0.35 | E6: 0.35 | F6: 0.35 | H6: 3 | I6: 8.0399 | J6: 9.5392 | K6: 9.5392 | L6: 10.5387 | M6: 10.5387 | O6: 3 | P6: 5.2505 | Q6: 8.2253 | R6: 5.1486 | S6: 7.3311 | T6: 5.55 | V6: 3 | W6: 2.6141 | X6: 3.3408 | Y6: 2.6609 | Z6: 3.0424 | AA6: 2.2812 | AC6: 3 | AD6: 0.4024 | AE6: 0.2904 | AF6: 0.2904 | AG6: 0.2156 | AH6: 0.2156
A7: 4 | B7: 0.5 | C7: 0.5 | D7: 0.5 | E7: 0.5 | F7: 0.5 | H7: 4 | I7: 7.6505 | J7: 9.2636 | K7: 9.2636 | L7: 10.3391 | M7: 10.3391 | O7: 4 | P7: 5.6493 | Q7: 8.85 | R7: 5.5396 | S7: 7.8878 | T7: 5.9715 | V7: 4 | W7: 2.8127 | X7: 3.5945 | Y7: 2.863 | Z7: 3.2735 | AA7: 2.4544 | AC7: 4 | AD7: 0.4312 | AE7: 0.3108 | AF7: 0.3108 | AG7: 0.2302 | AH7: 0.2302
A8: 5 | B8: 0.5 | C8: 0.5 | D8: 0.5 | E8: 0.5 | F8: 0.5 | H8: 5 | I8: 7.2328 | J8: 8.9688 | K8: 8.9688 | L8: 10.1261 | M8: 10.1261 | O8: 5 | P8: 6.0793 | Q8: 9.5236 | R8: 5.9613 | S8: 8.4883 | T8: 6.426 | V8: 5 | W8: 3.0268 | X8: 3.8681 | Y8: 3.0809 | Z8: 3.5226 | AA8: 2.6412 | AC8: 5 | AD8: 0.4622 | AE8: 0.3326 | AF8: 0.3326 | AG8: 0.2459 | AH8: 0.2459
A9: 6 | B9: 0.5 | C9: 0.5 | D9: 0.5 | E9: 0.5 | F9: 0.5 | H9: 6 | I9: 6.7848 | J9: 8.6533 | K9: 8.6533 | L9: 9.8989 | M9: 9.8989 | O9: 6 | P9: 6.5432 | Q9: 10.2505 | R9: 6.4162 | S9: 9.1361 | T9: 6.9164 | V9: 6 | W9: 2.2578 | X9: 3.1633 | Y9: 3.316 | Z9: 3.7915 | AA9: 2.8428 | AC9: 6 | AD9: 0.4954 | AE9: 0.3559 | AF9: 0.3559 | AG9: 0.2626 | AH9: 0.2626
A10: 7 | B10: 0.5 | C10: 0.5 | D10: 0.5 | E10: 0.5 | F10: 0.5 | H10: 7 | I10: 6.3043 | J10: 8.3157 | K10: 8.3157 | L10: 9.6568 | M10: 9.6568 | O10: 7 | P10: 7.0442 | Q10: 11.0352 | R10: 6.9074 | S10: 9.8355 | T10: 7.4459 | V10: 7 | W10: 1.4306 | X10: 2.4055 | Y10: 3.5699 | Z10: 4.0817 | AA10: 3.0604 | AC10: 7 | AD10: 0.531 | AE10: 0.3808 | AF10: 0.3808 | AG10: 0.2804 | AH10: 0.2804
A11: 8 | B11: 0.5571 | C11: 0.5333 | D11: 0.5333 | E11: 0.5235 | F11: 0.5235 | H11: 8 | I11: 5.7886 | J11: 7.9546 | K11: 7.9546 | L11: 9.3987 | M11: 9.3987 | O11: 8 | P11: 7.5854 | Q11: 11.883 | R11: 7.4381 | S11: 10.5911 | T11: 8.018 | V11: 8 | W11: 1.5405 | X11: 2.5903 | Y11: 3.8441 | Z11: 4.3953 | AA11: 3.2956 | AC11: 8 | AD11: 0.5693 | AE11: 0.4076 | AF11: 0.4076 | AG11: 0.2994 | AH11: 0.2994
A12: 9 | B12: 0.6143 | C12: 0.5667 | D12: 0.5667 | E12: 0.5471 | F12: 0.5471 | H12: 9 | I12: 5.2352 | J12: 7.5683 | K12: 7.5683 | L12: 9.1238 | M12: 9.1238 | O12: 9 | P12: 7.1706 | Q12: 11.7997 | R12: 8.0119 | S12: 11.4082 | T12: 8.6366 | V12: 9 | W12: 1.6594 | X12: 2.7901 | Y12: 3.1407 | Z12: 3.7344 | AA12: 3.5498 | AC12: 9 | AD12: 0.6104 | AE12: 0.4362 | AF12: 0.4362 | AG12: 0.3196 | AH12: 0.3196
A13: 10 | B13: 0.6714 | C13: 0.6 | D13: 0.6 | E13: 0.5706 | F13: 0.5706 | H13: 10 | I13: 4.641 | J13: 7.1549 | K13: 7.1549 | L13: 8.8309 | M13: 8.8309 | O13: 10 | P13: 6.6264 | Q13: 11.6144 | R13: 8.633 | S13: 12.2925 | T13: 9.306 | V13: 10 | W13: 1.788 | X13: 3.0064 | Y13: 2.3842 | Z13: 3.0239 | AA13: 3.825 | AC13: 10 | AD13: 0.6545 | AE13: 0.4668 | AF13: 0.4668 | AG13: 0.3412 | AH13: 0.3412
A14: 11 | B14: 0.7286 | C14: 0.6333 | D14: 0.6333 | E14: 0.5941 | F14: 0.5941 | H14: 11 | I14: 4.0026 | J14: 6.7125 | K14: 6.7125 | L14: 8.5191 | M14: 8.5191 | O14: 11 | P14: 5.9427 | Q14: 11.3194 | R14: 9.3057 | S14: 13.2504 | T14: 10.0312 | V14: 11 | W14: 0.9273 | X14: 2.2406 | Y14: 2.5699 | Z14: 3.2595 | AA14: 3.123 | AC14: 11 | AD14: 0.7019 | AE14: 0.4996 | AF14: 0.4996 | AG14: 0.3642 | AH14: 0.3642
A15: 12 | B15: 0.7857 | C15: 0.6667 | D15: 0.6667 | E15: 0.6176 | F15: 0.6176 | H15: 12 | I15: 3.3164 | J15: 6.2386 | K15: 6.2386 | L15: 8.1869 | M15: 8.1869 | O15: 12 | P15: 5.1085 | Q15: 10.9067 | R15: 9.0351 | S15: 13.289 | T15: 10.8175 | V15: 12 | W15: 0 | X15: 1.4163 | Y15: 2.7714 | Z15: 3.515 | AA15: 2.3678 | AC15: 12 | AD15: 0.753 | AE15: 0.5348 | AF15: 0.5348 | AG15: 0.3888 | AH15: 0.3888
A16: 13 | B16: 0.8429 | C16: 0.7 | D16: 0.7 | E16: 0.6412 | F16: 0.6412 | H16: 13 | I16: 2.578 | J16: 5.7308 | K16: 5.7308 | L16: 7.8328 | M16: 7.8328 | O16: 13 | P16: 4.1116 | Q16: 10.3671 | R16: 8.6479 | S16: 13.2374 | T16: 11.6709 | V16: 13 | W16: 0 | X16: 1.528 | Y16: 2.99 | Z16: 3.7923 | AA16: 2.5546 | AC16: 13 | AD16: 0.8079 | AE16: 0.5725 | AF16: 0.5725 | AG16: 0.415 | AH16: 0.415
... A18: 15 | B18: 0.9 | C18: 0.7667 | D18: 0.7667 | E18: 0.6882 | F18: 0.6882 | H18: 15 | I18: 0.9254 | J18: 4.6009 | K18: 4.6009 | L18: 7.0513 | M18: 7.0513 | O18: 15 | P18: 1.5732 | Q18: 8.8659 | R18: 7.4856 | S18: 12.836 | T18: 11.4258 | V18: 15 | W18: 0 | X18: 1.7813 | Y18: 1.4057 | Z18: 2.341 | AA18: 2.9781 | AC18: 15 | AD18: 0.931 | AE18: 0.6566 | AF18: 0.6566 | AG18: 0.473 | AH18: 0.473
A19: 16 | B19: 0 | C19: 0.8 | D19: 0.8 | E19: 0.7118 | F19: 0.7118 | H19: 16 | I19: 0 | J19: 3.9717 | K19: 3.9717 | L19: 6.6196 | M19: 6.6196 | O19: 16 | P19: 0 | Q19: 7.8804 | R19: 6.6889 | S19: 12.4706 | T19: 11.1466 | V19: 16 | W19: 0 | X19: 0.9249 | Y19: 1.519 | Z19: 2.5297 | AA19: 2.2182 | AC19: 16 | AE19: 0.7034 | AF19: 0.7034 | AG19: 0.505 | AH19: 0.505
A20: 17 | B20: 0 | C20: 0.8333 | D20: 0.8333 | E20: 0.7353 | F20: 0.7353 | H20: 17 | I20: 0 | J20: 3.2942 | K20: 3.2942 | L20: 6.1572 | M20: 6.1572 | O20: 17 | P20: 0 | Q20: 6.7203 | R20: 5.7321 | S20: 11.9832 | T20: 10.7518 | V20: 17 | W20: 0 | X20: 0 | Y20: 1.6424 | Z20: 2.7351 | AA20: 1.3983 | AC20: 17 | AE20: 0.7539 | AF20: 0.7539 | AG20: 0.5394 | AH20: 0.5394
A21: 18 | B21: 0 | C21: 0.8667 | D21: 0.8667 | E21: 0.7588 | F21: 0.7588 | H21: 18 | I21: 0 | J21: 2.5638 | K21: 2.5638 | L21: 5.661 | M21: 5.661 | O21: 18 | P21: 0 | Q21: 5.3702 | R21: 4.6011 | S21: 11.3637 | T21: 10.2315 | V21: 18 | W21: 0 | X21: 0 | Y21: 1.7768 | Z21: 2.9589 | AA21: 1.5127 | AC21: 18 | AE21: 0.8084 | AF21: 0.8084 | AG21: 0.5764 | AH21: 0.5764
A22: 19 | B22: 0 | C22: 0.9 | D22: 0.9 | E22: 0.7824 | F22: 0.7824 | H22: 19 | I22: 0 | J22: 1.7752 | K22: 1.7752 | L22: 5.1278 | M22: 5.1278 | O22: 19 | P22: 0 | Q22: 3.8131 | R22: 3.2805 | S22: 10.6007 | T22: 9.5752 | V22: 19 | W22: 0 | X22: 0 | Y22: 0.9233 | Z22: 2.2029 | AA22: 1.6374 | AC22: 19 | AE22: 0.8673 | AF22: 0.8673 | AG22: 0.6161 | AH22: 0.6161
A23: 20 | B23: 0 | C23: 0.9 | D23: 0.9 | E23: 0.8059 | F23: 0.8059 | H23: 20 | I23: 0 | J23: 0.9227 | K23: 0.9227 | L23: 4.5539 | M23: 4.5539 | O23: 20 | P23: 0 | Q23: 2.0299 | R23: 1.7531 | S23: 9.6817 | T23: 8.7709 | V23: 20 | W23: 0 | X23: 0 | Y23: 0 | Z23: 1.386 | AA23: 1.7735 | AC23: 20 | AE23: 0.931 | AF23: 0.931 | AG23: 0.659 | AH23: 0.659
A24: 21 | B24: 0 | C24: 0 | D24: 0 | E24: 0.8294 | F24: 0.8294 | H24: 21 | I24: 0 | J24: 0 | K24: 0 | L24: 3.9354 | M24: 3.9354 | O24: 21 | P24: 0 | Q24: 0 | R24: 0 | S24: 8.5928 | T24: 7.8057 | V24: 21 | W24: 0 | X24: 0 | Y24: 0 | Z24: 1.5021 | AA24: 0.9221 | AC24: 21 | AG24: 0.7052 | AH24: 0.7052
A25: 22 | B25: 0 | C25: 0 | D25: 0 | E25: 0.8529 | F25: 0.8529 | H25: 22 | I25: 0 | J25: 0 | K25: 0 | L25: 3.2679 | M25: 3.2679 | O25: 22 | P25: 0 | Q25: 0 | R25: 0 | S25: 7.3188 | T25: 6.6652 | V25: 22 | W25: 0 | X25: 0 | Y25: 0 | Z25: 1.629 | AA25: 0 | AC25: 22 | AG25: 0.7551 | AH25: 0.7551
A26: 23 | B26: 0 | C26: 0 | D26: 0 | E26: 0.8765 | F26: 0.8765 | H26: 23 | I26: 0 | J26: 0 | K26: 0 | L26: 2.5465 | M26: 2.5465 | O26: 23 | P26: 0 | Q26: 0 | R26: 0 | S26: 5.8426 | T26: 5.3333 | V26: 23 | W26: 0 | X26: 0 | Y26: 0 | Z26: 1.7679 | AA26: 0 | AC26: 23 | AG26: 0.8091 | AH26: 0.8091
A27: 24 | B27: 0 | C27: 0 | D27: 0 | E27: 0.9 | F27: 0.9 | H27: 24 | I27: 0 | J27: 0 | K27: 0 | L27: 1.7656 | M27: 1.7656 | O27: 24 | P27: 0 | Q27: 0 | R27: 0 | S27: 4.1455 | T27: 3.7923 | V27: 24 | W27: 0 | X27: 0 | Y27: 0 | Z27: 0.92 | AA27: 0 | AC27: 24 | AG27: 0.8675 | AH27: 0.8675
A28: 25 | B28: 0 | C28: 0 | D28: 0 | E28: 0.9 | F28: 0.9 | H28: 25 | I28: 0 | J28: 0 | K28: 0 | L28: 0.9191 | M28: 0.9191 | O28: 25 | P28: 0 | Q28: 0 | R28: 0 | S28: 2.2059 | T28: 2.0221 | V28: 25 | W28: 0 | X28: 0 | Y28: 0 | Z28: 0 | AA28: 0 | AC28: 25 | AG28: 0.931 | AH28: 0.931

Sheet MB
A1: PPT | B1: 7 | C1: 7 | D1: 10 | E1: 10 | F1: 12
A2: PT | B2: 15 | C2: 20 | D2: 20 | E2: 25 | F2: 25
A3: 18 | B3: 6.3379 | C3: 6.6886 | D3: 10.1546 | E3: 11.1627 | F3: 13.2353
A4: 19 | B4: 6.3359 | C4: 6.6846 | D4: 10.1522 | E4: 11.1597 | F4: 13.232
A5: 20 | B5: 6.3343 | C5: 6.6811 | D5: 10.1506 | E5: 11.158 | F5: 13.2298
A6: 21 | B6: 6.3329 | C6: 6.6775 | D6: 10.1494 | E6: 11.1569 | F6: 13.2283
A7: 22 | B7: 6.3314 | C7: 6.6737 | D7: 10.1485 | E7: 11.1561 | F7: 13.2269
A8: 23 | B8: 6.3297 | C8: 6.6692 | D8: 10.1473 | E8: 11.1552 | F8: 13.2253
A9: 24 | B9: 6.3275 | C9: 6.6637 | D9: 10.1457 | E9: 11.1537 | F9: 13.223
A10: 25 | B10: 6.3246 | C10: 6.657 | D10: 10.1433 | E10: 11.1514 | F10: 13.2196
A11: 26 | B11: 6.3209 | C11: 6.6488 | D11: 10.1401 | E11: 11.148 | F11: 13.215
A12: 27 | B12: 6.3162 | C12: 6.6388 | D12: 10.1357 | E12: 11.1432 | F12: 13.2088
A13: 28 | B13: 6.3104 | C13: 6.6268 | D13: 10.1301 | E13: 11.1369 | F13: 13.2008
A14: 29 | B14: 6.3033 | C14: 6.6123 | D14: 10.123 | E14: 11.1287 | F14: 13.1906
... A35: 50 | B35: 5.4138 | C35: 5.0354 | D35: 9.0652 | E35: 9.6514 | F35: 11.4836
A36: 51 | D36: 8.9184 | E36: 9.4242 | F36: 11.2258
A37: 52 | D37: 8.7578 | E37: 9.1696 | F37: 10.9345
A38: 53 | D38: 8.5828 | E38: 8.8822 | F38: 10.6073
A39: 54 | D39: 8.3922 | E39: 8.5596 | F39: 10.2392
A40: 55 | D40: 8.1839 | E40: 8.1955 | F40: 9.8223
A41: 56 | F41: 9.3435
A42: 57 | F42: 8.7908
A43: 58 | F43: 8.1456
A44: 59 | F44: 7.3767
A45: 60 | F45: 6.4268
B47: Deferred Income 30% - with 10% increase
A48: PPT | B48: 7 | C48: 7 | D48: 10 | E48: 10 | F48: 12
A49: PT | B49: 15 | C49: 20 | D49: 20 | E49: 25 | F49: 25
A50: 18 | B50: 7.5577 | C50: 6.4933 | D50: 14.4345 | E50: 15.1113 | F50: 20.9128
A51: 19 | B51: 7.5559 | C51: 6.49 | D51: 14.4332 | E51: 15.1111 | F51: 20.9128
A52: 20 | B52: 7.5547 | C52: 6.4872 | D52: 14.433 | E52: 15.1125 | F52: 20.9147
A53: 21 | B53: 7.5537 | C53: 6.4846 | D53: 14.4336 | E53: 15.1152 | F53: 20.9179
A54: 22 | B54: 7.5529 | C54: 6.482 | D54: 14.4346 | E54: 15.1188 | F54: 20.9221
A55: 23 | B55: 7.5519 | C55: 6.479 | D55: 14.4359 | E55: 15.123 | F55: 20.927
A56: 24 | B56: 7.5507 | C56: 6.4754 | D56: 14.4372 | E56: 15.1274 | F56: 20.9323
A57: 25 | B57: 7.5489 | C57: 6.4708 | D57: 14.4382 | E57: 15.132 | F57: 20.9377
A58: 26 | B58: 7.5464 | C58: 6.465 | D58: 14.4389 | E58: 15.1366 | F58: 20.9432
A59: 27 | B59: 7.5433 | C59: 6.4579 | D59: 14.439 | E59: 15.1412 | F59: 20.9487
A60: 28 | B60: 7.5392 | C60: 6.4491 | D60: 14.4386 | E60: 15.1456 | F60: 20.9541
A61: 29 | B61: 7.5342 | C61: 6.4385 | D61: 14.4375 | E61: 15.1497 | F61: 20.9594
... A82: 50 | B82: 6.8391 | C82: 5.2139 | D82: 13.9508 | E82: 14.7664 | F82: 20.5837
A83: 51 | D83: 13.8709 | E83: 14.6843 | F83: 20.4995
A84: 52 | D84: 13.7852 | E84: 14.5969 | F84: 20.4103
A85: 53 | D85: 13.6951 | E85: 14.5056 | F85: 20.3174
A86: 54 | D86: 13.6011 | E86: 14.4113 | F86: 20.2217
A87: 55 | D87: 13.5037 | E87: 14.3143 | F87: 20.1235
A88: 56 | F88: 20.0223
A89: 57 | F89: 19.9161
A90: 58 | F90: 19.8021
A91: 59 | F91: 19.6756
A92: 60 | F92: 19.5288
B94: Twin Income
A95: PPT | B95: 7 | C95: 7 | D95: 10 | E95: 10 | F95: 12
A96: PT | B96: 15 | C96: 20 | D96: 20 | E96: 25 | F96: 25
A97: 18 | B97: 5.0589 | C97: 3.8186 | D97: 10.5094 | E97: 11.3234 | F97: 18.2416
A98: 19 | B98: 5.0565 | C98: 3.813 | D98: 10.5073 | E98: 11.3212 | F98: 18.2405
A99: 20 | B99: 5.0546 | C99: 3.8073 | D99: 10.5062 | E99: 11.3202 | F99: 18.241
A100: 21 | B100: 5.0527 | C100: 3.8014 | D100: 10.5056 | E100: 11.3201 | F100: 18.2426
A101: 22 | B101: 5.0506 | C101: 3.7948 | D101: 10.5052 | E101: 11.3205 | F101: 18.245
A102: 23 | B102: 5.0482 | C102: 3.7872 | D102: 10.5049 | E102: 11.3209 | F102: 18.2477
A103: 24 | B103: 5.0451 | C103: 3.7781 | D103: 10.5042 | E103: 11.321 | F103: 18.2505
A104: 25 | B104: 5.0412 | C104: 3.7673 | D104: 10.503 | E104: 11.3206 | F104: 18.2531
A105: 26 | B105: 5.0363 | C105: 3.7544 | D105: 10.5011 | E105: 11.3195 | F105: 18.2555
A106: 27 | B106: 5.0303 | C106: 3.739 | D106: 10.4984 | E106: 11.3175 | F106: 18.2573
A107: 28 | B107: 5.023 | C107: 3.7207 | D107: 10.4947 | E107: 11.3144 | F107: 18.2586
A108: 29 | B108: 5.0143 | C108: 3.699 | D108: 10.4898 | E108: 11.3099 | F108: 18.2592
... A129: 50 | B129: 3.9818 | C129: 1.6109 | D129: 9.6366 | E129: 10.1791 | F129: 17.5265
A130: 51 | D130: 9.5119 | E130: 9.9929 | F130: 17.4017
A131: 52 | D131: 9.3753 | E131: 9.7838 | F131: 17.2662
A132: 53 | D132: 9.2265 | E132: 9.5496 | F132: 17.1203
A133: 54 | D133: 9.0648 | E133: 9.287 | F133: 16.9639
A134: 55 | D134: 8.8887 | E134: 8.9912 | F134: 16.7959
A135: 56 | F135: 16.6099
A136: 57 | F136: 16.3972
A137: 58 | F137: 16.1468
A138: 59 | F138: 15.8549
A139: 60 | F139: 15.5019
